{
  "url": "https://gatetest.roxybrowser.co/__ghost__/",
  "server": {
    "port": 2368,
    "host": "::"
  },
  "database": {
    "client": "mysql",
    "connection": {
      "host": "127.0.0.1",
      "port": 3306,
      "user": "root",
      "password": "4q7+,2c=!E8H^nmxY-L:",
      "database": "db_blog_server"
    }
  },
  "mail": {
    "transport": "SMTP",
    "from": "z_anbin@163.com",
    "options": {
      "service": "163",
      "auth": {
        "user": "z_anbin@163.com",
        "pass": "PDrqd7gBYVzvEvAS"
      }
    }
  },
  "logging": {
    "transports": [
      "file",
      "stdout"
    ]
  },
  "process": "systemd",
  "paths": {
    "contentPath": "/var/lib/ghost/content"
  }
}